crypto_drive_manager/__init__.py
crypto_drive_manager/cli.py
crypto_drive_manager/systemd.py
crypto_drive_manager-3.0.dist-info/DESCRIPTION.rst
crypto_drive_manager-3.0.dist-info/METADATA
crypto_drive_manager-3.0.dist-info/RECORD
crypto_drive_manager-3.0.dist-info/WHEEL
crypto_drive_manager-3.0.dist-info/entry_points.txt
crypto_drive_manager-3.0.dist-info/metadata.json
crypto_drive_manager-3.0.dist-info/top_level.txt
