Metadata-Version: 2.0
Name: crypto-drive-manager
Version: 3.0
Summary: Unlock all your encrypted drives with one pass phrase.
Home-page: https://github.com/xolox/python-crypto-drive-manager
Author: Peter Odding
Author-email: peter@peterodding.com
License: UNKNOWN
Platform: UNKNOWN
Classifier: Development Status :: 5 - Production/Stable
Classifier: Environment :: Console
Classifier: Intended Audience :: Information Technology
Classifier: Intended Audience :: System Administrators
Classifier: License :: OSI Approved :: MIT License
Classifier: Operating System :: POSIX :: Linux
Classifier: Programming Language :: Python
Classifier: Programming Language :: Python :: 2
Classifier: Programming Language :: Python :: 2.6
Classifier: Programming Language :: Python :: 2.7
Classifier: Programming Language :: Python :: 3
Classifier: Programming Language :: Python :: 3.4
Classifier: Topic :: Security :: Cryptography
Classifier: Topic :: System :: Filesystems
Classifier: Topic :: System :: Systems Administration
Classifier: Topic :: Terminals
Classifier: Topic :: Utilities
Requires-Dist: coloredlogs (>=7.3.1)
Requires-Dist: executor (>=1.6)
Requires-Dist: humanfriendly (>=1.36)
Requires-Dist: linux-utils (>=0.3)
Requires-Dist: verboselogs (>=1.7)
Requires-Dist: enum34 (>=1.1.6); python_version == "2.6" or python_version == "2.7" or python_version == "3.0" or python_version == "3.1" or python_version == "3.2" or python_version == "3.3"
